pulse_actions
