Metadata-Version: 1.1
Name: pulse-actions
Version: 0.1.3
Summary: A pulse listener that acts upon messages with mozci.
Home-page: https://github.com/adusca/pulse_actions
Author: Alice Scarpa
Author-email: alicescarpa@gmail.com
License: MPL 2.0
Platform: UNKNOWN
Classifier: Intended Audience :: Developers
Classifier: License :: OSI Approved :: Mozilla Public License 2.0 (MPL 2.0)
Classifier: Natural Language :: English
Classifier: Operating System :: OS Independent
Classifier: Programming Language :: Python
Classifier: Topic :: Software Development :: Libraries :: Python Modules
